maya_numerals/__init__.py
maya_numerals/mn.py
maya_numerals-0.0.1.dist-info/METADATA
maya_numerals-0.0.1.dist-info/WHEEL
maya_numerals-0.0.1.dist-info/licenses/LICENSE
maya_numerals-0.0.1.dist-info/RECORD
