Metadata-Version: 2.3
Name: maya_numerals
Version: 0.0.1
Summary: A package that converts numbers in Western digits into Maya numerical glyphs.
Project-URL: Homepage, https://github.com/ian-nai/maya_numerals
Project-URL: Bug Tracker, https://github.com/ian-nai/maya_numerals
Author-email: Ian Goodale <ianpgoodale@gmail.com>
License: GNU GENERAL PUBLIC LICENSE
License-File: LICENSE
Classifier: License :: OSI Approved :: GNU General Public License v3 (GPLv3)
Classifier: Operating System :: OS Independent
Classifier: Programming Language :: Python :: 3
Requires-Python: >=3.7
